{
    "scenebuilder": {
        "buildings": [
            {
                "ID": "B0",
                "vertices": [
                    [
                        -0.2258064516129039,
                        -0.790322580645161,
                        1.2
                    ],
                    [
                        -2.346774193548388,
                        -1.403225806451613,
                        1.2
                    ],
                    [
                        -1.419354838709678,
                        -0.12903225806451601,
                        1.2
                    ],
                    [
                        1.298387096774193,
                        0.217741935483871,
                        1.2
                    ]
                ]
            },
            {
                "ID": "B1",
                "vertices": [
                    [
                        1.330645161290322,
                        -3.161290322580645,
                        1.2
                    ],
                    [
                        0.4999999999999991,
                        -3.048387096774193,
                        1.2
                    ],
                    [
                        1.629032258064516,
                        -0.870967741935484,
                        1.2
                    ],
                    [
                        2.266129032258064,
                        -0.943548387096774,
                        1.2
                    ]
                ]
            }
        ],
        "vehicles": [
            {
                "ID": "V0",
                "position": [
                    -3.0000000000000004,
                    -3.008064516129032,
                    0.5
                ],
                "goal": [
                    2.693548387096774,
                    2.612903225806452,
                    0.5
                ]
            },
            {
                "ID": "V1",
                "position": [
                    -1.040322580645162,
                    2.564516129032258,
                    0.5
                ],
                "goal": [
                    -1.0000000000000009,
                    -2.983870967741935,
                    0.5
                ]
            },
            {
                "ID": "V2",
                "position": [
                    0.951612903225806,
                    -0.758064516129032,
                    0.5
                ],
                "goal": [
                    -2.919354838709678,
                    2.5,
                    0.5
                ]
            },
            {
                "ID": "V3",
                "position": [
                    2.61290322580645,
                    -2.951612903225806,
                    0.5
                ],
                "goal": [
                    -3.1532258064516134,
                    -0.435483870967742,
                    0.5
                ]
            }
        ]
    },
    "default": {
        "buildings": [
            {
                "ID": "Building 0",
                "vertices": [
                    [
                        0.0,
                        0.5,
                        1.2
                    ],
                    [
                        0.47552825814757677,
                        0.15450849718747373,
                        1.2
                    ],
                    [
                        0.2938926261462366,
                        -0.40450849718747367,
                        1.2
                    ],
                    [
                        -0.2938926261462365,
                        -0.4045084971874737,
                        1.2
                    ],
                    [
                        -0.4755282581475768,
                        0.15450849718747361,
                        1.2
                    ]
                ]
            }
        ],
        "vehicles": [
            {
                "ID": "V0",
                "position": [
                    -3.0,
                    0.0001,
                    0.5
                ],
                "goal": [
                    3.0,
                    0.0,
                    0.5
                ],
                "source_strength": 0.5,
                "imag_source_strength": 0.5,
                "sink_strength": 5
            }
        ]
    }
}